shadok/__init__.py
shadok/culture.py
shadok/language.py
shadok/logic.py
shadok/magic_faucet.py
shadok/mathematic.py
shadok/path_to_success.py
shadok/shadok_integer.py
shadok/shadok_string.py
shadok/tests/__init__.py
shadok/tests/generic_shadok_test.py
shadok/tests/test_culture.py
shadok/tests/test_language.py
shadok/tests/test_logic.py
shadok/tests/test_mathematics.py
shadok/tests/test_shadok_string.py
shadok-1.2.3.dist-info/LICENSE
shadok-1.2.3.dist-info/METADATA
shadok-1.2.3.dist-info/WHEEL
shadok-1.2.3.dist-info/top_level.txt
shadok-1.2.3.dist-info/RECORD
