Metadata-Version: 2.1
Name: shadok
Version: 1.2.3
Summary: Permit to unleash the full efficiency of shadok's logic in Python.
Home-page: https://github.com/Pierre-Sassoulas/shadok
Author: pierre-sassoulas
Author-email: pierre.sassoulas@gmail.com
License: UNKNOWN
Platform: UNKNOWN
Classifier: Programming Language :: Python :: 3
Classifier: License :: OSI Approved :: MIT License
Classifier: Operating System :: OS Independent
